{
    "transactionId": "6e881d97-6424-4fba-bbf6-4141917ca8fe",
    "timestamp": "637524864360214722",
    "greToClientEvent": {
        "greToClientMessages": [
            {
                "type": "GREMessageType_GameStateMessage",
                "systemSeatIds": [
                    2
                ],
                "msgId": 10,
                "gameStateId": 3,
                "gameStateMessage": {
                    "type": "GameStateType_Diff",
                    "gameStateId": 3,
                    "players": [
                        {
                            "lifeTotal": 20,
                            "systemSeatNumber": 1,
                            "maxHandSize": 7,
                            "teamId": 1,
                            "timerIds": [
                                1,
                                2,
                                3,
                                4,
                                5,
                                6
                            ],
                            "controllerSeatId": 1,
                            "controllerType": "ControllerType_Player",
                            "startingLifeTotal": 20
                        }
                    ],
                    "turnInfo": {
                        "activePlayer": 1,
                        "decisionPlayer": 2
                    },
                    "pendingMessageCount": 2,
                    "prevGameStateId": 2,
                    "timers": [
                        {
                            "timerId": 1,
                            "type": "TimerType_Prologue",
                            "durationSec": 120,
                            "elapsedSec": 18,
                            "behavior": "TimerBehavior_TakeControl",
                            "warningThresholdSec": 30,
                            "elapsedMs": 18782
                        },
                        {
                            "timerId": 5,
                            "type": "TimerType_Inactivity",
                            "durationSec": 150,
                            "behavior": "TimerBehavior_Timeout",
                            "warningThresholdSec": 130
                        },
                        {
                            "timerId": 7,
                            "type": "TimerType_Prologue",
                            "durationSec": 120,
                            "running": true,
                            "behavior": "TimerBehavior_TakeControl",
                            "warningThresholdSec": 30,
                            "elapsedMs": 1
                        },
                        {
                            "timerId": 11,
                            "type": "TimerType_Inactivity",
                            "durationSec": 150,
                            "running": true,
                            "behavior": "TimerBehavior_Timeout",
                            "warningThresholdSec": 130,
                            "elapsedMs": 1
                        }
                    ],
                    "update": "GameStateUpdate_SendAndRecord",
                    "actions": [
                        {
                            "seatId": 2,
                            "action": {
                                "actionType": "ActionType_Cast",
                                "instanceId": 225,
                                "manaCost": [
                                    {
                                        "color": [
                                            "ManaColor_Generic"
                                        ],
                                        "count": 1
                                    },
                                    {
                                        "color": [
                                            "ManaColor_Blue"
                                        ],
                                        "count": 1
                                    }
                                ]
                            }
                        },
                        {
                            "seatId": 2,
                            "action": {
                                "actionType": "ActionType_Play",
                                "instanceId": 222
                            }
                        },
                        {
                            "seatId": 2,
                            "action": {
                                "actionType": "ActionType_Play",
                                "instanceId": 224
                            }
                        },
                        {
                            "seatId": 2,
                            "action": {
                                "actionType": "ActionType_Play",
                                "instanceId": 219
                            }
                        },
                        {
                            "seatId": 2,
                            "action": {
                                "actionType": "ActionType_Play",
                                "instanceId": 220
                            }
                        },
                        {
                            "seatId": 2,
                            "action": {
                                "actionType": "ActionType_Play",
                                "instanceId": 221
                            }
                        },
                        {
                            "seatId": 2,
                            "action": {
                                "actionType": "ActionType_Play",
                                "instanceId": 223
                            }
                        }
                    ]
                }
            },
            {
                "type": "GREMessageType_PromptReq",
                "systemSeatIds": [
                    1,
                    2
                ],
                "msgId": 11,
                "gameStateId": 3,
                "prompt": {
                    "promptId": 37,
                    "parameters": [
                        {
                            "parameterName": "PlayerId",
                            "type": "ParameterType_Reference",
                            "reference": {
                                "type": "ReferenceType_PlayerSeatId",
                                "id": 1
                            }
                        }
                    ]
                }
            },
            {
                "type": "GREMessageType_MulliganReq",
                "systemSeatIds": [
                    2
                ],
                "msgId": 12,
                "gameStateId": 3,
                "prompt": {
                    "promptId": 34,
                    "parameters": [
                        {
                            "parameterName": "NumberOfCards",
                            "type": "ParameterType_Number",
                            "numberValue": 7
                        }
                    ]
                },
                "mulliganReq": {
                    "mulliganType": "MulliganType_London"
                }
            }
        ]
    }
}